linkedin_spider/__init__.py
linkedin_spider/__main__.py
linkedin_spider/assets/banner.txt
linkedin_spider/assets/spider.txt
linkedin_spider/cli/__init__.py
linkedin_spider/cli/commands.py
linkedin_spider/cli/display.py
linkedin_spider/cli/extract_cookies.py
linkedin_spider/cli/main.py
linkedin_spider/core/__init__.py
linkedin_spider/core/browser.py
linkedin_spider/core/google_search.py
linkedin_spider/core/profile_parser.py
linkedin_spider/core/scraper.py
linkedin_spider/core/worker.py
linkedin_spider/db/__init__.py
linkedin_spider/db/client.py
linkedin_spider/db/models.py
linkedin_spider/models/__init__.py
linkedin_spider/models/profile.py
linkedin_spider/queue/__init__.py
linkedin_spider/queue/consumer.py
linkedin_spider/queue/producer.py
linkedin_spider/utils/__init__.py
linkedin_spider/utils/config.py
linkedin_spider/utils/export.py
linkedin_spider/utils/logger.py
linkedin_spider/utils/session.py
linkedin_spider/utils/vpn.py
linkedin_tarantula-0.1.0.dist-info/LICENSE
linkedin_tarantula-0.1.0.dist-info/METADATA
linkedin_tarantula-0.1.0.dist-info/WHEEL
linkedin_tarantula-0.1.0.dist-info/entry_points.txt
linkedin_tarantula-0.1.0.dist-info/RECORD
