Metadata-Version: 2.3
Name: linkedin-tarantula
Version: 0.1.0
Summary: A professional CLI tool for scraping LinkedIn profiles via Google Search (linkedin-spider was taken)
License: MIT
Keywords: linkedin,scraper,cli,automation,web-scraping
Author: quantium
Author-email: alexcollsoutumuro@gmail.com
Requires-Python: >=3.9,<4.0
Classifier: Development Status :: 3 - Alpha
Classifier: Intended Audience :: Developers
Classifier: License :: OSI Approved :: MIT License
Classifier: Programming Language :: Python :: 3
Classifier: Programming Language :: Python :: 3.9
Classifier: Programming Language :: Python :: 3.10
Classifier: Programming Language :: Python :: 3.11
Classifier: Programming Language :: Python :: 3.12
Classifier: Programming Language :: Python :: 3.13
Provides-Extra: excel
Requires-Dist: beautifulsoup4 (>=4.12.3,<5.0.0)
Requires-Dist: lxml (>=5.3.0,<6.0.0)
Requires-Dist: openpyxl (>=3.1.5,<4.0.0) ; extra == "excel"
Requires-Dist: pandas (>=2.2.3,<3.0.0)
Requires-Dist: python-dotenv (>=1.0.1,<2.0.0)
Requires-Dist: pyyaml (>=6.0.2,<7.0.0)
Requires-Dist: rich (>=13.9.4,<14.0.0)
Requires-Dist: selenium (>=4.26.1,<5.0.0)
Requires-Dist: typer (>=0.15.1,<0.16.0)
Requires-Dist: webdriver-manager (>=4.0.2,<5.0.0)
Project-URL: Repository, https://github.com/quantium/linkedin-spider
